autoauth.py
setup.py
autoauth.egg-info/PKG-INFO
autoauth.egg-info/SOURCES.txt
autoauth.egg-info/dependency_links.txt
autoauth.egg-info/pbr.json
autoauth.egg-info/requires.txt
autoauth.egg-info/top_level.txt