Metadata-Version: 1.0
Name: autoauth
Version: 1.0.2
Summary: authentication in urllib2 and requests for the command line
Home-page: UNKNOWN
Author: David Keijser
Author-email: keijser@gmail.com
License: MIT
Keywords: requests urllib2 authenticate
Platform: UNKNOWN
